{"nodes": [{"id": "apps_api_src_tests_helpers_fixtures_ts", "label": "fixtures.ts", "file_type": "code", "source_file": "apps\\api\\src\\tests\\helpers\\fixtures.ts", "source_location": "L1"}, {"id": "fixtures_userrow", "label": "userRow()", "file_type": "code", "source_file": "apps\\api\\src\\tests\\helpers\\fixtures.ts", "source_location": "L22"}, {"id": "fixtures_projectrow", "label": "projectRow()", "file_type": "code", "source_file": "apps\\api\\src\\tests\\helpers\\fixtures.ts", "source_location": "L32"}, {"id": "fixtures_memberrow", "label": "memberRow()", "file_type": "code", "source_file": "apps\\api\\src\\tests\\helpers\\fixtures.ts", "source_location": "L55"}, {"id": "fixtures_commentrow", "label": "commentRow()", "file_type": "code", "source_file": "apps\\api\\src\\tests\\helpers\\fixtures.ts", "source_location": "L71"}, {"id": "fixtures_orgrow", "label": "orgRow()", "file_type": "code", "source_file": "apps\\api\\src\\tests\\helpers\\fixtures.ts", "source_location": "L93"}, {"id": "fixtures_orgmemberrow", "label": "orgMemberRow()", "file_type": "code", "source_file": "apps\\api\\src\\tests\\helpers\\fixtures.ts", "source_location": "L104"}, {"id": "fixtures_activityrow", "label": "activityRow()", "file_type": "code", "source_file": "apps\\api\\src\\tests\\helpers\\fixtures.ts", "source_location": "L116"}, {"id": "fixtures_suggestionrow", "label": "suggestionRow()", "file_type": "code", "source_file": "apps\\api\\src\\tests\\helpers\\fixtures.ts", "source_location": "L132"}, {"id": "fixtures_portalrow", "label": "portalRow()", "file_type": "code", "source_file": "apps\\api\\src\\tests\\helpers\\fixtures.ts", "source_location": "L152"}, {"id": "fixtures_exportrow", "label": "exportRow()", "file_type": "code", "source_file": "apps\\api\\src\\tests\\helpers\\fixtures.ts", "source_location": "L165"}, {"id": "fixtures_layerrow", "label": "layerRow()", "file_type": "code", "source_file": "apps\\api\\src\\tests\\helpers\\fixtures.ts", "source_location": "L179"}], "edges": [{"source": "apps_api_src_tests_helpers_fixtures_ts", "target": "fixtures_userrow", "relation": "contains", "confidence": "EXTRACTED", "source_file": "apps\\api\\src\\tests\\helpers\\fixtures.ts", "source_location": "L22", "weight": 1.0}, {"source": "apps_api_src_tests_helpers_fixtures_ts", "target": "fixtures_projectrow", "relation": "contains", "confidence": "EXTRACTED", "source_file": "apps\\api\\src\\tests\\helpers\\fixtures.ts", "source_location": "L32", "weight": 1.0}, {"source": "apps_api_src_tests_helpers_fixtures_ts", "target": "fixtures_memberrow", "relation": "contains", "confidence": "EXTRACTED", "source_file": "apps\\api\\src\\tests\\helpers\\fixtures.ts", "source_location": "L55", "weight": 1.0}, {"source": "apps_api_src_tests_helpers_fixtures_ts", "target": "fixtures_commentrow", "relation": "contains", "confidence": "EXTRACTED", "source_file": "apps\\api\\src\\tests\\helpers\\fixtures.ts", "source_location": "L71", "weight": 1.0}, {"source": "apps_api_src_tests_helpers_fixtures_ts", "target": "fixtures_orgrow", "relation": "contains", "confidence": "EXTRACTED", "source_file": "apps\\api\\src\\tests\\helpers\\fixtures.ts", "source_location": "L93", "weight": 1.0}, {"source": "apps_api_src_tests_helpers_fixtures_ts", "target": "fixtures_orgmemberrow", "relation": "contains", "confidence": "EXTRACTED", "source_file": "apps\\api\\src\\tests\\helpers\\fixtures.ts", "source_location": "L104", "weight": 1.0}, {"source": "apps_api_src_tests_helpers_fixtures_ts", "target": "fixtures_activityrow", "relation": "contains", "confidence": "EXTRACTED", "source_file": "apps\\api\\src\\tests\\helpers\\fixtures.ts", "source_location": "L116", "weight": 1.0}, {"source": "apps_api_src_tests_helpers_fixtures_ts", "target": "fixtures_suggestionrow", "relation": "contains", "confidence": "EXTRACTED", "source_file": "apps\\api\\src\\tests\\helpers\\fixtures.ts", "source_location": "L132", "weight": 1.0}, {"source": "apps_api_src_tests_helpers_fixtures_ts", "target": "fixtures_portalrow", "relation": "contains", "confidence": "EXTRACTED", "source_file": "apps\\api\\src\\tests\\helpers\\fixtures.ts", "source_location": "L152", "weight": 1.0}, {"source": "apps_api_src_tests_helpers_fixtures_ts", "target": "fixtures_exportrow", "relation": "contains", "confidence": "EXTRACTED", "source_file": "apps\\api\\src\\tests\\helpers\\fixtures.ts", "source_location": "L165", "weight": 1.0}, {"source": "apps_api_src_tests_helpers_fixtures_ts", "target": "fixtures_layerrow", "relation": "contains", "confidence": "EXTRACTED", "source_file": "apps\\api\\src\\tests\\helpers\\fixtures.ts", "source_location": "L179", "weight": 1.0}]}