{"nodes": [{"id": "gaez_futures_inventory", "label": "GAEZ Futures Inventory", "file_type": "document", "source_file": "apps/api/data/gaez/futures-inventory.md", "source_location": null, "source_url": null, "captured_at": null, "author": null, "contributor": null}], "edges": [{"source": "gaez_futures_inventory", "target": "soilgrids_readme", "relation": "semantically_similar_to", "confidence": "INFERRED", "confidence_score": 0.7, "source_file": "apps/api/data/gaez/futures-inventory.md", "source_location": null, "weight": 1.0}], "hyperedges": []}