{"nodes": [{"id": "apps_web_src_features_spiritual_solarcalc_ts", "label": "solarCalc.ts", "file_type": "code", "source_file": "apps\\web\\src\\features\\spiritual\\solarCalc.ts", "source_location": "L1"}, {"id": "solarcalc_computesolartimes", "label": "computeSolarTimes()", "file_type": "code", "source_file": "apps\\web\\src\\features\\spiritual\\solarCalc.ts", "source_location": "L27"}, {"id": "solarcalc_computeseasonaltable", "label": "computeSeasonalTable()", "file_type": "code", "source_file": "apps\\web\\src\\features\\spiritual\\solarCalc.ts", "source_location": "L82"}, {"id": "solarcalc_formattime", "label": "formatTime()", "file_type": "code", "source_file": "apps\\web\\src\\features\\spiritual\\solarCalc.ts", "source_location": "L104"}, {"id": "solarcalc_tojuliandate", "label": "toJulianDate()", "file_type": "code", "source_file": "apps\\web\\src\\features\\spiritual\\solarCalc.ts", "source_location": "L111"}, {"id": "solarcalc_fromjuliandate", "label": "fromJulianDate()", "file_type": "code", "source_file": "apps\\web\\src\\features\\spiritual\\solarCalc.ts", "source_location": "L122"}], "edges": [{"source": "apps_web_src_features_spiritual_solarcalc_ts", "target": "solarcalc_computesolartimes", "relation": "contains", "confidence": "EXTRACTED", "source_file": "apps\\web\\src\\features\\spiritual\\solarCalc.ts", "source_location": "L27", "weight": 1.0}, {"source": "apps_web_src_features_spiritual_solarcalc_ts", "target": "solarcalc_computeseasonaltable", "relation": "contains", "confidence": "EXTRACTED", "source_file": "apps\\web\\src\\features\\spiritual\\solarCalc.ts", "source_location": "L82", "weight": 1.0}, {"source": "apps_web_src_features_spiritual_solarcalc_ts", "target": "solarcalc_formattime", "relation": "contains", "confidence": "EXTRACTED", "source_file": "apps\\web\\src\\features\\spiritual\\solarCalc.ts", "source_location": "L104", "weight": 1.0}, {"source": "apps_web_src_features_spiritual_solarcalc_ts", "target": "solarcalc_tojuliandate", "relation": "contains", "confidence": "EXTRACTED", "source_file": "apps\\web\\src\\features\\spiritual\\solarCalc.ts", "source_location": "L111", "weight": 1.0}, {"source": "apps_web_src_features_spiritual_solarcalc_ts", "target": "solarcalc_fromjuliandate", "relation": "contains", "confidence": "EXTRACTED", "source_file": "apps\\web\\src\\features\\spiritual\\solarCalc.ts", "source_location": "L122", "weight": 1.0}, {"source": "solarcalc_computesolartimes", "target": "solarcalc_tojuliandate", "relation": "calls", "confidence": "EXTRACTED", "source_file": "apps\\web\\src\\features\\spiritual\\solarCalc.ts", "source_location": "L28", "weight": 1.0}, {"source": "solarcalc_computesolartimes", "target": "solarcalc_fromjuliandate", "relation": "calls", "confidence": "EXTRACTED", "source_file": "apps\\web\\src\\features\\spiritual\\solarCalc.ts", "source_location": "L64", "weight": 1.0}]}