{"nodes": [{"id": "apps_web_src_lib_climateprojections_ts", "label": "climateProjections.ts", "file_type": "code", "source_file": "apps\\web\\src\\lib\\climateProjections.ts", "source_location": "L1"}, {"id": "climateprojections_findregion", "label": "findRegion()", "file_type": "code", "source_file": "apps\\web\\src\\lib\\climateProjections.ts", "source_location": "L106"}, {"id": "climateprojections_computeclimateprojections", "label": "computeClimateProjections()", "file_type": "code", "source_file": "apps\\web\\src\\lib\\climateProjections.ts", "source_location": "L114"}, {"id": "climateprojections_buildadvisory", "label": "buildAdvisory()", "file_type": "code", "source_file": "apps\\web\\src\\lib\\climateProjections.ts", "source_location": "L171"}], "edges": [{"source": "apps_web_src_lib_climateprojections_ts", "target": "climateprojections_findregion", "relation": "contains", "confidence": "EXTRACTED", "source_file": "apps\\web\\src\\lib\\climateProjections.ts", "source_location": "L106", "weight": 1.0}, {"source": "apps_web_src_lib_climateprojections_ts", "target": "climateprojections_computeclimateprojections", "relation": "contains", "confidence": "EXTRACTED", "source_file": "apps\\web\\src\\lib\\climateProjections.ts", "source_location": "L114", "weight": 1.0}, {"source": "apps_web_src_lib_climateprojections_ts", "target": "climateprojections_buildadvisory", "relation": "contains", "confidence": "EXTRACTED", "source_file": "apps\\web\\src\\lib\\climateProjections.ts", "source_location": "L171", "weight": 1.0}, {"source": "climateprojections_computeclimateprojections", "target": "climateprojections_findregion", "relation": "calls", "confidence": "EXTRACTED", "source_file": "apps\\web\\src\\lib\\climateProjections.ts", "source_location": "L120", "weight": 1.0}, {"source": "climateprojections_computeclimateprojections", "target": "climateprojections_buildadvisory", "relation": "calls", "confidence": "EXTRACTED", "source_file": "apps\\web\\src\\lib\\climateProjections.ts", "source_location": "L145", "weight": 1.0}]}