{"nodes": [{"id": "apps_web_src_lib_companionplanting_ts", "label": "companionPlanting.ts", "file_type": "code", "source_file": "apps\\web\\src\\lib\\companionPlanting.ts", "source_location": "L1"}, {"id": "companionplanting_normalize", "label": "normalize()", "file_type": "code", "source_file": "apps\\web\\src\\lib\\companionPlanting.ts", "source_location": "L355"}, {"id": "companionplanting_findcompanions", "label": "findCompanions()", "file_type": "code", "source_file": "apps\\web\\src\\lib\\companionPlanting.ts", "source_location": "L412"}, {"id": "companionplanting_companionmatrixcoverage", "label": "companionMatrixCoverage()", "file_type": "code", "source_file": "apps\\web\\src\\lib\\companionPlanting.ts", "source_location": "L418"}], "edges": [{"source": "apps_web_src_lib_companionplanting_ts", "target": "companionplanting_normalize", "relation": "contains", "confidence": "EXTRACTED", "source_file": "apps\\web\\src\\lib\\companionPlanting.ts", "source_location": "L355", "weight": 1.0}, {"source": "apps_web_src_lib_companionplanting_ts", "target": "companionplanting_findcompanions", "relation": "contains", "confidence": "EXTRACTED", "source_file": "apps\\web\\src\\lib\\companionPlanting.ts", "source_location": "L412", "weight": 1.0}, {"source": "apps_web_src_lib_companionplanting_ts", "target": "companionplanting_companionmatrixcoverage", "relation": "contains", "confidence": "EXTRACTED", "source_file": "apps\\web\\src\\lib\\companionPlanting.ts", "source_location": "L418", "weight": 1.0}, {"source": "companionplanting_findcompanions", "target": "companionplanting_normalize", "relation": "calls", "confidence": "EXTRACTED", "source_file": "apps\\web\\src\\lib\\companionPlanting.ts", "source_location": "L413", "weight": 1.0}]}